<?xml version="1.0" encoding="UTF-8" ?>
<content><string id="body">Выпущено исправление, устраняющее проблемы в рейтинговой игре.

[list]
[*]Исправлено, что топтание личинок засчитывается как убийство жука в местах, для которых это не предназначалось, например, в достижениях «Подрывник» и «Усиленный урон».
[*]Fixed marines getting stuck in fire extinguisher particles, staircases, and terrain.
[/list]</string><string id="subtitle"></string><string id="summary"></string><string id="title">Обновление Alien Swarm: Reactive Drop - 19 января 2023 года</string></content>